Adafruit_BMP-1.5.2.dist-info/metadata.json
Adafruit_BMP-1.5.2.dist-info/METADATA
Adafruit_BMP-1.5.2.dist-info/RECORD
Adafruit_BMP-1.5.2.dist-info/WHEEL
Adafruit_BMP-1.5.2.dist-info/DESCRIPTION.rst
Adafruit_BMP-1.5.2.dist-info/dependency_links.txt
Adafruit_BMP-1.5.2.dist-info/top_level.txt
Adafruit_BMP/BMP085.py
Adafruit_BMP/__init__.py
